{
  "@pnp/generator-spfx": {
    "framework": "react",
    "pnpFramework": "reactjs.plus",
    "pnp-libraries": [
      "@pnp/pnpjs"
    ],
    "pnp-ci": [],
    "pnp-vetting": [],
    "spfxenv": "spo"
  },
  "@microsoft/generator-sharepoint": {
    "environment": "spo",
    "framework": "react",
    "isCreatingSolution": true,
    "version": "1.8.0",
    "libraryName": "sp-fxjest",
    "libraryId": "3132d8e7-c5dd-438a-a2f2-0f491793a488",
    "packageManager": "npm",
    "isDomainIsolated": false,
    "componentType": "webpart"
  }
}